[
    {
        "code": "f62e",
        "severity": "Warning",
        "title": "XC-Wildcard port on virtual not supported in XC",
        "message": "XC-Multiport LBs are not supported yet",
        "regex": "(?<=add (?:cs|lb) vserver [\\S]+ [\\S]+ [\\d.]+ )(0)"
    },
    {
        "code": "62ff",
        "severity": "Warning",
        "title": "XC-Wildcard VIP not supported",
        "message": "XC-Wildcard VIPs not supported",
        "regex": "(?<=add (?:cs|lb) vserver [\\S]+ [\\S]+ )(0.0.0.0)(?= \\d{1,5})"
    },
    {
        "code": "72fb",
        "severity": "Information",
        "title": "AppFlow reference detected",
        "message": "AppFlow, similar to sflow, has been detected on this app (add more details about appflow/sflow)",
        "regex": "add appflow (?:policy|action|collector)"
    },
    {
        "code": "cb78",
        "severity": "Error",
        "title": "XC-FTP not supported?",
        "message": "so, look for tcp ports 21/22",
        "regex": "ftp"
    },
    {
        "code": "a2ea",
        "severity": "Error",
        "title": "App with match across services",
        "message": "XC cannot match across services, like ftp, control on tcp/21, data on tcp/22",
        "regex": "match-across-(pools|services|virtuals) enabled"
    },
    {
        "code": "6a1e",
        "severity": "Warning",
        "title": "Static NAT not supported",
        "message": "XC can nat, but uses a range of sources -- refine the regex ",
        "regex": "snat"
    },
    {
        "code": "2245",
        "severity": "Warning",
        "title": "snat pool object detected",
        "message": "NATs are supported, but not statics",
        "regex": "ltm snatpool"
    },
    {
        "code": "3a67",
        "severity": "Error",
        "title": "Supporting APM profile detected",
        "message": "While not a direct APM profile, these profiles on the VS indicate that an APM profile is applied",
        "regex": "(/Common/websso { }|/Common/rba { })"
    },
    {
        "code": "4987",
        "severity": "Error",
        "title": "no classmatch allowed in iRule",
        "message": "not really XC but will cause problems",
        "regex": "classmatch"
    },
    {
        "code": "5a5a",
        "severity": "Error",
        "title": "iRule stream profile detected",
        "message": "F5 TMOS stream profile functionality not supported",
        "regex": "stream::"
    },
    {
        "code": "0780",
        "severity": "Warning",
        "title": "XC reserved ports",
        "message": "Http failure response: 400 Bad Request \nFor tcp_loadbalancer dude/test configuration for child object advertise_policy ves-io-tcp-loadbalancer-test-df9979789 is wrong - 8443 is a reserved port, list of reserved ports 28000 - 32767 (kubernetes),28000 - 32767 (volterra),2379,9090,9999,18091,22222,23790,23791,1067,2380,8005,18092,9153,10250,10252,10259,500,8007,8443,10251,18095,23801,5355,8507,9007,68,323,23802,8444,8505,10249,10257,22,4500,8087,18093,53,6443,10256",
        "regex": "/(?=.*destination)(:(8443|2379|9090|9999|18091|22222|23790|23791|1067|2380|8005|18092|9153|10250|10252|10259|500|8007|10251|18095|23801|5355|8507|9007|68|323|23802|8444|8505|10249|10257|22|4500|8087|18093|53|6443|10256))/si"
    },
    {
        "code": "d2bf",
        "severity": "Error",
        "title": "XC UDP Unsupported",
        "message": "XC does not currently support UDP *** does ns support udp? ***",
        "regex": "ip-protocol udp"
    },
    {
        "code": "a188",
        "severity": "Information",
        "title": "Default Redirect iRule Detected",
        "message": "The default http->https redirect irule has been detected.",
        "regex": "/Common/_sys_https_redirect"
    },
    {
        "code": "5617",
        "severity": "Information",
        "title": "",
        "message": "",
        "regex": ""
    },
    {
        "code": "4818",
        "severity": "Warning",
        "title": "",
        "message": "",
        "regex": ""
    },
    {
        "code": "681f",
        "severity": "Warning",
        "title": "",
        "message": "",
        "regex": ""
    },
    {
        "code": "3955",
        "severity": "Error",
        "title": "",
        "message": "",
        "regex": ""
    },
    {
        "code": "f6e2",
        "severity": "Hint",
        "title": "",
        "message": "",
        "regex": ""
    },
    {
        "code": "b02f",
        "severity": "Hint",
        "title": "",
        "message": "",
        "regex": ""
    },
    {
        "code": "b3c7",
        "severity": "Hint",
        "title": "",
        "message": "",
        "regex": ""
    },
    {
        "code": "fd5c",
        "severity": "Hint",
        "title": "",
        "message": "",
        "regex": ""
    },
    {
        "code": "df8b",
        "severity": "Hint",
        "title": "",
        "message": "",
        "regex": ""
    },
    {
        "code": "57ef",
        "severity": "Hint",
        "title": "",
        "message": "",
        "regex": ""
    },
    {
        "code": "0f93",
        "severity": "Hint",
        "title": "",
        "message": "",
        "regex": ""
    },
    {
        "code": "0a0a",
        "severity": "Hint",
        "title": "",
        "message": "",
        "regex": ""
    },
    {
        "code": "e90c",
        "severity": "Hint",
        "title": "",
        "message": "",
        "regex": ""
    },
    {
        "code": "5ca0",
        "severity": "Hint",
        "title": "",
        "message": "",
        "regex": ""
    },
    {
        "code": "81b2",
        "severity": "Hint",
        "title": "",
        "message": "",
        "regex": ""
    },
    {
        "code": "016e",
        "severity": "Hint",
        "title": "",
        "message": "",
        "regex": ""
    },
    {
        "code": "232e",
        "severity": "Hint",
        "title": "",
        "message": "",
        "regex": ""
    },
    {
        "code": "33a5",
        "severity": "Hint",
        "title": "",
        "message": "",
        "regex": ""
    },
    {
        "code": "e1ca",
        "severity": "Hint",
        "title": "",
        "message": "",
        "regex": ""
    },
    {
        "code": "940f",
        "severity": "Hint",
        "title": "",
        "message": "",
        "regex": ""
    },
    {
        "code": "79ee",
        "severity": "Hint",
        "title": "",
        "message": "",
        "regex": ""
    },
    {
        "code": "9f4b",
        "severity": "Hint",
        "title": "",
        "message": "",
        "regex": ""
    },
    {
        "code": "70c1",
        "severity": "Hint",
        "title": "",
        "message": "",
        "regex": ""
    },
    {
        "code": "4c7b",
        "severity": "Hint",
        "title": "",
        "message": "",
        "regex": ""
    },
    {
        "code": "b3d3",
        "severity": "Hint",
        "title": "",
        "message": "",
        "regex": ""
    },
    {
        "code": "849c",
        "severity": "Hint",
        "title": "",
        "message": "",
        "regex": ""
    },
    {
        "code": "b164",
        "severity": "Hint",
        "title": "",
        "message": "",
        "regex": ""
    },
    {
        "code": "06cf",
        "severity": "Hint",
        "title": "",
        "message": "",
        "regex": ""
    },
    {
        "code": "a0f3",
        "severity": "Hint",
        "title": "",
        "message": "",
        "regex": ""
    },
    {
        "code": "ae47",
        "severity": "Hint",
        "title": "",
        "message": "",
        "regex": ""
    },
    {
        "code": "4680",
        "severity": "Hint",
        "title": "",
        "message": "",
        "regex": ""
    },
    {
        "code": "bc0c",
        "severity": "Hint",
        "title": "",
        "message": "",
        "regex": ""
    },
    {
        "code": "251f",
        "severity": "Hint",
        "title": "",
        "message": "",
        "regex": ""
    },
    {
        "code": "1e73",
        "severity": "Hint",
        "title": "",
        "message": "",
        "regex": ""
    },
    {
        "code": "dd4d",
        "severity": "Hint",
        "title": "",
        "message": "",
        "regex": ""
    },
    {
        "code": "9981",
        "severity": "Hint",
        "title": "",
        "message": "",
        "regex": ""
    },
    {
        "code": "3790",
        "severity": "Hint",
        "title": "",
        "message": "",
        "regex": ""
    }
]